docs_scraper/__init__.py
docs_scraper/main.py
docs_scraper/markdown_converter.py
docs_scraper/webscraper.py
docs_scraper-0.1.2.dist-info/METADATA
docs_scraper-0.1.2.dist-info/WHEEL
docs_scraper-0.1.2.dist-info/entry_points.txt
docs_scraper-0.1.2.dist-info/top_level.txt
docs_scraper-0.1.2.dist-info/RECORD
