Metadata-Version: 2.4
Name: docs_scraper
Version: 0.1.2
Summary: Need to scrape documentation pages from the url
Requires-Python: >=3.12
Requires-Dist: beautifulsoup4>=4.14.2
Requires-Dist: docling>=2.57.0
